{
  "project_info": {
    "project_number": "1060360359056",
    "firebase_url": "https://namegamekotlin.firebaseio.com",
    "project_id": "namegamekotlin",
    "storage_bucket": "namegamekotlin.appspot.com"
  },
  "client": [
    {
      "client_info": {
        "mobilesdk_app_id": "1:1060360359056:android:e41adf9f4239973b",
        "android_client_info": {
          "package_name": "com.willowtreeapps.namegame"
        }
      },
      "oauth_client": [
        {
          "client_id": "1060360359056-jg12tcoe1i1pi66u90ed0fths0o6p54q.apps.googleusercontent.com",
          "client_type": 1,
          "android_info": {
            "package_name": "com.willowtreeapps.namegame",
            "certificate_hash": "d92149ce680e55fcc9c0c4e12732362dad84a718"
          }
        },
        {
          "client_id": "1060360359056-99i0vklp7js0vpahpetks2njas0srsfd.apps.googleusercontent.com",
          "client_type": 3
        }
      ],
      "api_key": [
        {
          "current_key": "AIzaSyA--LTJY3hBLRCyvTDwnqmCTKssXDkl0jo"
        }
      ],
      "services": {
        "appinvite_service": {
          "other_platform_oauth_client": [
            {
              "client_id": "1060360359056-99i0vklp7js0vpahpetks2njas0srsfd.apps.googleusercontent.com",
              "client_type": 3
            }
          ]
        }
      }
    }
  ],
  "configuration_version": "1"
}